{
	"type" : "FeatureCollection",
	"name" : "public.gsbz_pumpstaton",
	"features" : [
		{
			"type" : "Feature",
			"geometry" : {
				"type" : "Point",
				"coordinates" : [ 113.5283788, 34.808928 ]
			},
			"properties" : {
				"smid" : 560,
				"smuserid" : 0,
				"fcode" : null,
				"eid" : "GS-BZ-0000560",
				"expno" : null,
				"mapno" : null,
				"mapcode" : null,
				"fname" : null,
				"category" : null,
				"subtype" : null,
				"sur_h" : null,
				"carea" : null,
				"descapacity" : null,
				"rwscapacity" : null,
				"despressure" : null,
				"rwspressure" : null,
				"servicereg" : null,
				"prequipment" : null,
				"pump_num" : null,
				"work_stats" : null,
				"principal" : null,
				"ptel" : null,
				"cov_date" : null,
				"finish_date" : null,
				"survey_date" : null,
				"survey_person" : null,
				"managedept" : null,
				"bunit" : null,
				"sunit" : null,
				"constructer" : null,
				"prjid" : null,
				"prjname" : null,
				"prjtype" : null,
				"prjunit" : null,
				"prjperson" : null,
				"lane_way" : null,
				"addr" : null,
				"io_ds" : null,
				"archive_id" : null,
				"datatype" : null,
				"add_person" : "张明亮",
				"add_date" : "20250414092417+08:00",
				"write_person" : "张明亮",
				"write_date" : "20250414092427+08:00",
				"check_person" : null,
				"remark" : null,
				"x" : 12637921.316,
				"y" : 4137945.444,
				"gname" : "中原区",
				"grid" : "0110",
				"district" : null,
				"impid" : null,
				"globalid" : "8bac1b81-ba50-47c6-9f13-ff6d2eeaab94"
			}
		},
		{
			"type" : "Feature",
			"geometry" : {
				"type" : "Point",
				"coordinates" : [ 113.5443149, 34.8058295 ]
			},
			"properties" : {
				"smid" : 579,
				"smuserid" : 0,
				"fcode" : null,
				"eid" : "GS-BZ-000579",
				"expno" : null,
				"mapno" : null,
				"mapcode" : null,
				"fname" : null,
				"category" : null,
				"subtype" : null,
				"sur_h" : 0,
				"carea" : 0,
				"descapacity" : null,
				"rwscapacity" : null,
				"despressure" : null,
				"rwspressure" : null,
				"servicereg" : null,
				"prequipment" : null,
				"pump_num" : null,
				"work_stats" : null,
				"principal" : null,
				"ptel" : null,
				"cov_date" : null,
				"finish_date" : null,
				"survey_date" : null,
				"survey_person" : null,
				"managedept" : null,
				"bunit" : null,
				"sunit" : null,
				"constructer" : null,
				"prjid" : null,
				"prjname" : null,
				"prjtype" : null,
				"prjunit" : null,
				"prjperson" : null,
				"lane_way" : null,
				"addr" : null,
				"io_ds" : null,
				"archive_id" : null,
				"datatype" : null,
				"add_person" : "测试用户",
				"add_date" : "20250509115051+08:00",
				"write_person" : null,
				"write_date" : null,
				"check_person" : null,
				"remark" : null,
				"x" : 12639695.316,
				"y" : 4137525.359,
				"gname" : "中原区",
				"grid" : "0110",
				"district" : null,
				"impid" : null,
				"globalid" : "{D1B558D1-4FE5-4FB6-8065-6C1B2E4615D0}"
			}
		}
	]
}